kedab/__init__.py
kedab/activation.py
kedab/activation_layer.py
kedab/enum_optimizer.py
kedab/enum_regularization.py
kedab/fc_layer.py
kedab/layer.py
kedab/loss.py
kedab/neural.py
kedab-0.1.7.dist-info/METADATA
kedab-0.1.7.dist-info/WHEEL
kedab-0.1.7.dist-info/top_level.txt
kedab-0.1.7.dist-info/RECORD
